xgenius/__init__.py
xgenius/cli.py
xgenius/utils.py
xgenius/sbatch_templates/slurm_account_template.sbatch
xgenius/sbatch_templates/slurm_partition_template.sbatch
xgenius/scripts/__init__.py
xgenius/scripts/batch_submit.py
xgenius/scripts/build_image.py
xgenius/scripts/cancel_jobs.py
xgenius/scripts/check_jobs.py
xgenius/scripts/generate_run_config.py
xgenius/scripts/pull_repos.py
xgenius/scripts/pull_results.py
xgenius/scripts/remove_results.py
xgenius/scripts/setup_clusters.py
xgenius/scripts/sync_repos.py
xgenius-0.3.0.dist-info/METADATA
xgenius-0.3.0.dist-info/WHEEL
xgenius-0.3.0.dist-info/entry_points.txt
xgenius-0.3.0.dist-info/top_level.txt
xgenius-0.3.0.dist-info/RECORD
