Metadata-Version: 2.1
Name: xgenius
Version: 0.3.0
Summary: A tool for managing cluster jobs and configurations
Home-page: https://github.com/roger-creus/xgenius
Author: Roger Creus Castanyer
Author-email: creus99@gmail.com
Classifier: Programming Language :: Python :: 3
Classifier: License :: OSI Approved :: MIT License
Classifier: Operating System :: OS Independent
Requires-Dist: rich
Requires-Dist: paramiko
Requires-Dist: scp
